{
  "@type": "Recipe",
  "identifier": "boston-chicken-squash",
  "name": "Pollo de Boston con calabacín",
  "recipeCuisine": "Non-regional",
  "recipeCategory": "Fruits, Grains & Vegetables",
  "keywords": [
    "misceláneo",
    "verduras"
  ],
  "recipeIngredient": [
    "2 calabazas butternut (cortadas por la mitad y sin semillas)",
    "Manteca o mantequilla",
    "Sal",
    "1/2 taza de azúcar moreno (en bloque)",
    "1/2 taza de miel",
    "1/2 cucharadita de jengibre molido",
    "1 cucharadita de especias para pastel de calabaza",
    "4 cucharadas de mantequilla o manteca derretida"
  ],
  "recipeInstructions": "1. Precalentar el horno a 200 °C.\n2. Colocar las calabazas, corte hacia abajo, en una bandeja de hornear poco profunda engrasada con spray antiadherente.\n3. Hornear sin cubrir durante aproximadamente 45 minutos o hasta que sean tiernas al pincharlas con un tenedor.\n4. Limpiar la superficie cortada con un poco de mantequilla y espolvorear con sal.\n5. Devolverlas al horno, corte hacia arriba, durante unos 10 minutos más o hasta que estén doradas y blandas.\n6. Retirar la carne y colocarla en un bol.\n7. Agregar el azúcar, miel, jengibre, especias para pastel de calabaza y mantequilla al bol.\n8. Batir con una batidora eléctrica a velocidad media hasta que quede suave.\n9. Devolver la mezcla al horno, cubierta con papel de aluminio, durante 30 minutos para mantenerla caliente hasta el momento de servir.\n10. Refrigerar los sobras durante aproximadamente una semana o congelar hasta 4 meses.",
  "url": null
}
