{
  "@type": "Recipe",
  "identifier": "tangy-fruit-gelatin",
  "name": "Gelatina de frutas ácidas",
  "recipeCuisine": "Non-regional",
  "recipeCategory": "Fruits, Grains & Vegetables",
  "keywords": [
    "queso",
    "frutas",
    "gelatina",
    "ensaladas"
  ],
  "recipeIngredient": [
    "3 tazas de agua",
    "1 sobre grande de gelatina de sabor a melocotón",
    "8 onzas de yogur natural",
    "3 onzas de queso crema, ablandado y cortado en cubos",
    "6 onzas de concentrado de limonada congelada (descongelado)",
    "Fresas",
    "Frambuesas",
    "Arándanos",
    "Uvas",
    "Rodajas de melocotón"
  ],
  "recipeInstructions": "1. En una cacerola pequeña, hierve el agua.\n2. Disuelve la gelatina en el agua hirviendo.\n3. Vierte 2 tazas y 1/4 de la mezcla de gelatina caliente en un recipiente de licuadora.\n4. Reserva 1 taza y 1/4 de la mezcla de gelatina restante.\n5. Agrega el yogur, el queso crema y el concentrado de limonada a la mezcla de gelatina en la licuadora; licúa hasta obtener una textura suave.\n6. Vierte la mezcla en un molde de vidrio para tartas o quiches de 10 pulgadas.\n7. Refrigera hasta que esté firme.\n8. Coloca las frutas sobre la gelatina.\n9. Refrigera la mezcla de gelatina reservada hasta que espese lo suficiente para cubrir una cuchara.\n10. Vierte cuidadosamente la gelatina espesa sobre las frutas para cubrirlas uniformemente.\n11. Cubre y refrigera durante la noche, o hasta que esté cuajada.",
  "url": null
}
