{
  "@type": "Recipe",
  "identifier": "warm-salad-of-clams-and-cockles-with-escarole-rhubarb",
  "name": "Ensalada tibia de almejas y mejillones con escarola y ruibarbo",
  "recipeCuisine": "Non-regional",
  "recipeCategory": "Fruits, Grains & Vegetables",
  "keywords": [
    "ensaladas"
  ],
  "recipeIngredient": [
    "4 cucharadas de aceite de oliva virgen extra",
    "2 dientes de ajo, cortados finamente",
    "1 taza de ruibarbo en juliana",
    "12 almejas pequeñas (littleneck)",
    "1 taza de vino blanco seco",
    "20 mejillones",
    "2 cucharadas de mantequilla",
    "2 cucharadas de vinagre de vino tinto",
    "1 cabeza de escarola, cortada en tiras de 1 cm",
    "2 pimientos rojos asados, pelados, sin semillas y cortados en juliana fina",
    "1 cucharada de pasta de aceituna negra",
    "12 rebanadas finas de baguette tostadas"
  ],
  "recipeInstructions": "1. En una sartén antiadherente de 30 a 35 cm, calienta el aceite de oliva hasta que humee.\n2. Añade el ajo y el ruibarbo; cocina hasta que se ablanden, aproximadamente 4-5 minutos.\n3. Agrega las almejas pequeñas y el vino blanco; lleva a ebullición.\n4. Tapa y reduce el fuego. Deja cocinar hasta que todas las almejas estén abiertas, unos 6-8 minutos.\n5. Mientras tanto, prepara los crostini mezclando los pimientos asados, la pasta de aceituna y el aceite restante.\n- Divide la mezcla entre las rebanadas tostadas de baguette.\n- Coloca tres rebanadas en los bordes de cada uno de cuatro platos.\n6. Añade los mejillones a la sartén con las almejas; tapa.\n7. Cocina hasta que se abran los mejillones, aproximadamente 1 minuto.\n8. Incorpora el vinagre y la escarola; sazónala con sal y pimienta.\n9. Mezcla bien, luego divide la escarola, las almejas y los mejillones entre los platos.\n10. Sirve.\nRinde: 4 porciones",
  "url": null
}
