{
  "@type": "Recipe",
  "identifier": "grandma-aldrete-s-enchilada-sauce",
  "name": "Grandma Aldrete's Enchilada Sauce",
  "recipeCuisine": "Non-regional",
  "recipeCategory": "On the Side",
  "keywords": [
    "sauces",
    "side dishes"
  ],
  "recipeIngredient": [
    "3/4 cup Crisco",
    "1/4 cup flour",
    "1/4 cup chili powder",
    "2 cups tomato sauce",
    "2 cups stock or water",
    "2 tablespoons (tbsp) sugar",
    "2 pinches oregano",
    "2 pinches cumin"
  ],
  "recipeInstructions": "1. Melt the Crisco.\n2. Add the flour and stir until smooth.\n3. Mix the chili powder with 1 cup of water.\n4. Combine this mixture with the sauce mix.\n5. Gradually add the tomato sauce and 2 cups of stock or water.\n6. Stir in the sugar, salt, and spices.\n7. Simmer the sauce for a few minutes until it thickens slightly.",
  "url": null
}
