{
  "@type": "Recipe",
  "identifier": "maccaroncelli-alla-quintiere-macaroni-with-cheese",
  "name": "Maccaroncelli Alla Quintiere (Macaroni with Cheese)",
  "recipeCuisine": "Europe",
  "recipeCategory": "On the Side",
  "keywords": [
    "ethnic",
    "italian",
    "pasta",
    "sauces"
  ],
  "recipeIngredient": [
    "4 tbsp Butter",
    "1 Onion, chopped",
    "1 Stalk Celery, chopped",
    "1/2 Green Pepper, diced",
    "1 Tomato, peeled and chopped",
    "4 oz Gorgonzola Cheese, diced",
    "2 oz Chicken Broth",
    "2 tbsp Parmesan Cheese, grated",
    "2 tbsp Romano Cheese, grated",
    "2 oz White Wine",
    "8 oz Macaroni, cooked and drained"
  ],
  "recipeInstructions": "1. Melt the butter in a large frypan over medium heat.\n2. Add the onion, green pepper, and celery to the pan. Sauté until golden brown.\n3. Stir in the chopped tomato and simmer for 5 minutes.\n4. Add the diced Gorgonzola cheese and cook over low heat until melted.\n5. Once the cheese has melted, add the chicken broth, grated Parmesan and Romano cheeses, and white wine to the pan.\n6. Simmer the sauce for an additional 5 minutes.\n7. Drain the cooked macaroni well, then add it to the frypan with the sauce.\n8. Toss the pasta until fully coated in the sauce.\n9. Serve immediately.",
  "url": null
}
