{
  "@type": "Recipe",
  "identifier": "mango-salsa-jurassic",
  "name": "Mango Salsa (Jurassic)",
  "recipeCuisine": "Non-regional",
  "recipeCategory": "On the Side",
  "keywords": [
    "salsa",
    "salsas",
    "side dishes"
  ],
  "recipeIngredient": [
    "2 Whole mangos",
    "2/3 cup Chopped red bell pepper",
    "2/3 cup Chopped green bell pepper",
    "1 tbsp Minced seeded jalapeno",
    "or Serrano pepper",
    "1 tsp Salt",
    "1/2 tsp Pepper"
  ],
  "recipeInstructions": "1. Peel two 14- to 16-ounce ripe but firm mangos.\n2. Cut the flesh away from the center pit and dice.\n3. Place the diced mangoes in a medium bowl.\n4. Add chopped sweet peppers to the bowl.\n5. Stir in the minced jalapeno (or serrano pepper) and seasonings.\n6. Gently toss until well combined.\n7. Refrigerate for 1 to 3 hours before serving.\n(Note: Recipe by Jurassic Cove Cafe / Philip Costner, executive chef (1996))",
  "url": null
}
