{
  "@type": "Recipe",
  "identifier": "piccalilli-2",
  "name": "Piccalilli",
  "recipeCuisine": "Non-regional",
  "recipeCategory": "On the Side",
  "keywords": [
    "relishes",
    "side dishes"
  ],
  "recipeIngredient": [
    "4 Green Tomatoes",
    "2/3 Cup Salt",
    "1 Cup Horseradish, Grated",
    "2 Tablespoons Cinnamon",
    "2 Tablespoons Ground Cloves",
    "2 Tablespoons Allspice",
    "2 Tablespoons Dry Mustard",
    "2 Tablespoons Pepper",
    "Vinegar",
    "2 Cups Brown Sugar"
  ],
  "recipeInstructions": "1. Sprinkle salt over chopped tomatoes and let stand overnight.\n2. In the morning, drain in a colander.\n3. Add horseradish, spices, sugar, and enough vinegar to cover.\n4. Bring to a boil and cook for 20 minutes.\n5. Pour into sterilized jars and seal.",
  "url": null
}
