{
  "@type": "Recipe",
  "identifier": "piri-piri-sauce-3",
  "name": "Piri-Piri Sauce",
  "recipeCuisine": "Non-regional",
  "recipeCategory": "On the Side",
  "keywords": [
    "sauces",
    "side dishes"
  ],
  "recipeIngredient": [
    "3/4 cup Olive oil",
    "8.00 Chilli peppers with tops removed",
    "1 Bay leaf",
    "1 Small piece lemon rind"
  ],
  "recipeInstructions": "1. Pour the olive oil into a small, screw-top jar.\n2. Add the chili peppers (without their tops), bay leaf, and lemon rind to the jar.\n3. Secure the lid tightly on the jar.\n4. Shake well to combine all ingredients.\n5. Allow the mixture to stand in a warm place for at least 24 hours before using.\n6. The sauce can be stored at room temperature indefinitely.\nReady-made Piri-Piri sauce can be purchased by the Portuguese, who use it frequently as a spicy condiment over pasta, fish, or meat dishes, and also to flavor stews.",
  "url": null
}
