{
  "@type": "Recipe",
  "identifier": "rhubarb-bread-pudding-2",
  "name": "Rhubarb Bread Pudding",
  "recipeCuisine": "Non-regional",
  "recipeCategory": "On the Side",
  "keywords": [
    "desserts",
    "puddings",
    "side dishes"
  ],
  "recipeIngredient": [
    "4 Bread slices",
    "3 tablespoons Butter",
    "1/2 cup Sugar, granulated",
    "3/4 teaspoon Cinnamon",
    "3 cups Rhubarb, cut into 1-inch pieces"
  ],
  "recipeInstructions": "1. Spread each slice of bread with 1 teaspoon of butter.\n2. Cut the buttered bread into half-inch cubes.\n3. Combine sugar and cinnamon in a bowl.\n4. Arrange half of the rhubarb pieces in the bottom of a greased 8-inch baking dish.\n5. Top with half of the bread cubes and half of the sugar mixture.\n6. Repeat steps 4 and 5.\n7. Dot the remaining butter over the top layer.\n8. Cover and bake at 375°F for 20 minutes.\n9. Uncover and bake for an additional 20 to 25 minutes, or until lightly browned.",
  "url": null
}
