{
  "@type": "Recipe",
  "identifier": "tomato-ketchup-3",
  "name": "Tomato Ketchup",
  "recipeCuisine": "Non-regional",
  "recipeCategory": "On the Side",
  "keywords": [
    "condiments",
    "relishes",
    "side dishes"
  ],
  "recipeIngredient": [
    "10 pounds tomato; dead-ripe",
    "1 bell pepper, red; seeded & chopped",
    "4 large onion; chopped",
    "1 1/2 cups vinegar, cider",
    "2 garlic cloves; crushed",
    "1 teaspoon peppercorns",
    "1 teaspoon allspice, whole",
    "1 teaspoon cloves, whole",
    "5 cinnamon sticks",
    "1 teaspoon celery seed",
    "1/2 teaspoon mustard, dry",
    "1/4 teaspoon cayenne",
    "4 tablespoons sugar, brown; packed firm",
    "3 tablespoons sugar, granulated",
    "1 teaspoon salt"
  ],
  "recipeInstructions": "1. Cut tomatoes into quarters and puree them in a food processor along with the bell pepper.\n2. Strain the puree through a coarse sieve to remove skins and seeds. (You can dump the puree into a colander and work it through with your hands until there is nothing left in the colander but a dryish pulp of skins and seeds.)\n3. Puree onions, combine with tomato and pepper puree, and pour into a large stainless steel or enameled kettle.\n4. Cook and stir occasionally over low heat until it is reduced by about a third and is considerably thicker.\n5. Meanwhile, put garlic, peppercorns, allspice, cloves, cinnamon, and celery seed into the vinegar in a small pot and simmer covered for 1/2 hour to steep spices in the vinegar.\n6. Pour about half the spiced vinegar through a tea strainer into the thickened tomato mixture. Stir.\n7. Also add sugar, mustard, cayenne, and salt at this point.\n8. Taste and adjust ingredients as desired. Cook some more, stirring often, until it looks like ketchup should look.\n9. If it looks slightly curdled, process in a food processor to smooth out.\n10. Pour into sterile jars leaving 1/8 inch of head space.\n11. Process in a boiling water bath for 15 minutes.",
  "url": null
}
