{
  "@type": "Recipe",
  "identifier": "clams-casino-4",
  "name": "Clams Casino",
  "recipeCuisine": "Non-regional",
  "recipeCategory": "Snacks & Appetizers",
  "keywords": [
    "aperitivos",
    "emeril",
    "étnico",
    "mariscos",
    "tentempiés"
  ],
  "recipeIngredient": [
    "24 almejas Littleneck grandes",
    "8 oz de mantequilla de ajo compuesta",
    "1 taza de salchicha andouille desmenuzada",
    "1/2 taza de migas de pan",
    "6 lonchas de tocino; cortadas en trozos de 5 cm"
  ],
  "recipeInstructions": "1. Precalentar el horno a 400 °F (200 °C).\n2. Colocar las almejas en un paño y insertar un cuchillo entre las conchas.\n3. Separar las conchas, cortar el músculo de la bisagra y desechar la concha superior.\n4. Desprender el músculo de la concha inferior.\n5. Cortar la mantequilla compuesta en 24 trozos iguales.\n6. Colocar un trozo de mantequilla sobre cada almeja.\n7. En un procesador de alimentos, mezclar la salchicha andouille desmenuzada y las migas de pan hasta que estén completamente incorporadas.\n8. Sazonar con Esencia.\n9. Extender una cucharada de la mezcla de corteza sobre cada concha de almeja.\n10. Con las manos, presionar firmemente la corteza en la concha de la almeja.\n11. Cubrir cada concha con los trozos de tocino.\n12. Colocar en una bandeja para hornear y hornear durante 4-6 minutos.\n13. Retirar del horno.\n14. Colocar las almejas en una fuente y decorar con perejil y Esencia.",
  "url": null
}
