{
  "@type": "Recipe",
  "identifier": "cajun-tofu",
  "name": "Cajun Tofu",
  "recipeCuisine": "North & South America",
  "recipeCategory": "Restricted & Special Diets",
  "keywords": [
    "american",
    "cajun",
    "ethnic",
    "vegetarian"
  ],
  "recipeIngredient": [
    "2 lb Firm tofu, drained and cut into 3/4-inch cubes",
    "1 medium Red bell pepper, finely chopped (about 1/2 cup)",
    "1 medium Green bell pepper, finely chopped (about 1/2 cup)",
    "1 large White onion, finely chopped (1 cup)",
    "1 cup Chopped celery",
    "2 cans cooked/peeled tomatoes",
    "4 Cans tomato sauce",
    "1 gallon water (3/4 gallon for thicker soup)",
    "2 tbsp Finely chopped parsley",
    "1/2 cup Finely sliced green onion tops",
    "2 tbsp Worcestershire sauce",
    "2 tsp Salt",
    "2 1/2 tsp Red pepper flakes",
    "2 1/2 tsp Black pepper",
    "2 tsp Garlic salt",
    "3 tsp Paprika"
  ],
  "recipeInstructions": "1. Fry tofu in very hot olive or peanut oil until sealed.\n2. Pour the oil into a stock pot, adding enough to cover the bottom if necessary.\n3. Make a roux by adding an equal amount of flour and cooking until thickened.\n4. Add chopped peppers, onion, celery, tomatoes, tomato sauce, water, Worcestershire sauce, salt, red pepper flakes, black pepper, garlic salt, and paprika.\n5. Simmer for 25 minutes.\n6. Add the drained tofu, place the lid on the pot, and simmer for another 30 minutes, stirring occasionally.\n7. Add 3 or 4 fresh bay leaves and let cool for 15 minutes.\n8. Reheat if necessary and serve over steamed rice. Top with fresh parsley.\n9. If a less spicy mix is desired, reduce the amount of red pepper flakes to taste.",
  "url": null
}
