{
  "@type": "Recipe",
  "identifier": "vegetable-and-coconut-curry",
  "name": "Vegetable and Coconut Curry",
  "recipeCuisine": "Non-regional",
  "recipeCategory": "Restricted & Special Diets",
  "keywords": [
    "curries",
    "ethnic",
    "meatless",
    "special diets",
    "spices",
    "vegetarian"
  ],
  "recipeIngredient": [
    "15 g Butter",
    "1/2 liter Onion",
    "1 Green chili",
    "1 Garlic clove",
    "1 tsp Grated Ginger",
    "1/2 tsp Turmeric",
    "1/2 tsp Ground Cardamom",
    "1/2 tsp Ground Cinnamon",
    "1 cup Coconut Milk",
    "1 Strip of Lemon Rind",
    "62.5 g Green Beans",
    "1/2 Green Pepper",
    "1/2 Red Pepper",
    "1/4 Cup Cauliflower",
    "1 1/2 Zucchini (Courgettes)",
    "62.5 g Yellow Squash",
    "2 Potatoes",
    "1/4 cup Coconut Cream",
    "1/4 cup Coriander Leaves"
  ],
  "recipeInstructions": "1. Finely chop the green chili.\n2. Crush the garlic clove.\n3. Trim the green beans.\n4. Cut the peppers into strips.\n5. Cut the cauliflower into florets.\n6. Cut the zucchini into rounds.\n7. Cut the yellow squash into halves.\n8. Dice the potatoes.\n9. Chop the coriander leaves.\n10. In a large heavy-based pan, melt the butter over low heat.\n11. Add the onion and cook until soft.\n12. Add the green chili, garlic, and ginger; stir for 3-4 minutes.\n13. Stir in cardamom, turmeric, and cinnamon; cook, stirring, for 2-3 minutes.\n14. Add the coconut milk and lemon rind. Simmer gently, uncovered, for 10 minutes.\n15. Add the vegetables and cook, uncovered, until tender.\n16. Stir in the coconut cream and simmer for an additional 5 minutes.\n17. Serve on a large platter, garnished with fresh coriander leaves.",
  "url": null
}
