{
  "@type": "Recipe",
  "identifier": "amocha-sponge-cake-2",
  "name": "Amocha Sponge Cake",
  "recipeCuisine": "Non-regional",
  "recipeCategory": "Sweets & Desserts",
  "keywords": [
    "baked goods",
    "cakes",
    "chocolate",
    "desserts"
  ],
  "recipeIngredient": [
    "7 Eggs; separated",
    "1/2 tsp Salt",
    "1 cup Nuts; finely chopped",
    "1/4 cup Potato starch",
    "1/2 cup Strong coffee",
    "1 1/4 cups Sugar",
    "2 tsp Cocoa",
    "3/4 cup Cake meal"
  ],
  "recipeInstructions": "1. Pour hot coffee over the finely chopped nuts and let cool.\n2. Add 2 teaspoons cocoa to the cooled nut mixture.\n3. Beat egg whites with salt until they form soft peaks.\n4. Gradually add sugar while continuing to beat until stiff peaks form.\n5. Whisk yolks well, then add the remaining sugar, beating until thick.\n6. Mix in the coffee and nut mixture into the yolk mixture, blending well.\n7. Sift together the cake meal and potato starch, then fold into the batter.\n8. Pour the batter into a tube pan and bake at 325°F for 1 hour or longer.",
  "url": null
}
