{
  "@type": "Recipe",
  "identifier": "eggnog-pie-in-pecan-crust",
  "name": "Eggnog Pie in Pecan Crust",
  "recipeCuisine": "Non-regional",
  "recipeCategory": "Sweets & Desserts",
  "keywords": [
    "baked goods",
    "desserts",
    "pies"
  ],
  "recipeIngredient": [
    "Pecan Crust",
    "2 1/2 cups Ground pecans (9oz)",
    "1/3 cup Granulated sugar",
    "1/4 cup Butter, melted, unsalted",
    "Egg Nog Filling",
    "2 packages Unflavored gelatin",
    "1/4 cup Cold water",
    "2 tablespoons Brandy",
    "6 Egg yolks",
    "1/2 cup Granulated sugar",
    "2 cups Scalded milk",
    "2 teaspoons Vanilla extract",
    "1/4 cup Dark rum",
    "1 cup Heavy cream",
    "Cream Topping",
    "1 cup Heavy cream",
    "2 tablespoons Confectioners sugar",
    "Chocolate curls and Raspberries for garnish"
  ],
  "recipeInstructions": "Pecan Crust:\nButter a 10-inch pie plate. In a medium bowl, combine pecans, sugar, and melted butter. Mix well. Press firmly into the pie plate. Cover and refrigerate for 30 minutes while preheating the oven to 375°F (190°C). Bake the crust until lightly browned (about 15-20 minutes).\nEgg Nog Filling:\nIn a small bowl, sprinkle gelatin over cold water and brandy, allowing it to soften. In a separate small mixing bowl, combine egg yolks and sugar in an electric mixer at high speed until the mixture forms ribbons when beaters are lifted. Pour this into a large heavy saucepan and stir in hot milk slowly, cooking over medium-low heat while stirring constantly, until the mixture thickens enough to coat the spoon (and/or thermometer registers 172°F). Do not boil. Remove from heat and stir in softened gelatin until dissolved. Stir in vanilla and rum. Pour the custard into a medium bowl set into a larger bowl of ice water and allow it to cool, stirring frequently. When it begins to set around the edges but is still slightly warm, remove from the ice bath (do not let it set completely). In the chilled bowl, beat cream to soft peaks and gradually fold into the custard. If necessary, refrigerate briefly until the filling mounds when spooned.\nPile the filling into the crust and refrigerate until set (about an hour).\nCream Topping:\nIn a chilled medium bowl, whip cream and confectioners sugar to stiff peaks and pile on top of the pie. Garnish with chocolate curls and raspberries.",
  "url": null
}
