{
  "@type": "Recipe",
  "identifier": "grasshopper-parfaits",
  "name": "Grasshopper Parfaits",
  "recipeCuisine": "North & South America",
  "recipeCategory": "Sweets & Desserts",
  "keywords": [
    "alcohol",
    "american",
    "chocolate",
    "desserts"
  ],
  "recipeIngredient": [
    "1/2 cup Heavy cream",
    "1 tbsp Granulated sugar",
    "1 package Cream cheese -- softened",
    "1 1/4 cups Sweetened condensed milk --",
    "14 oz Can",
    "3 tbsp Lemon juice",
    "3 tbsp Green Creme de menthe",
    "Liqueur",
    "2 tbsp White Creme de cacao",
    "Liqueur",
    "12 each Cream filled chocolate Sandwich cookies -- coarsely chopped"
  ],
  "recipeInstructions": "1. In a small mixing bowl, whip cream until soft. Add sugar and beat until stiff.\n2. In a large mixing bowl, beat cream cheese until fluffy. Gradually beat in sweetened condensed milk. Stir in lemon juice and liqueurs.\n3. Fold in whipped cream; chill for 20 minutes.\n4. In parfait glasses, layer 1 tablespoon cookies and 1/4 cup filling. Repeat layers.\n5. Top with remaining cookies. Chill for 4 hours.\nVariations:\nCoffee: Substitute coffee-flavored liqueur for Creme de menthe.\nBrandy Alexander: Substitute 1/3 brandy for Creme de menthe.\nOrange: Omit Creme de cacao and substitute 1/4 cup orange liqueur for Creme de menthe.",
  "url": null
}
