{
  "@type": "Recipe",
  "identifier": "olive-garden-chocolate-chip-cookie-dough-chee",
  "name": "Olive Garden Chocolate Chip Cookie Dough Chee",
  "recipeCuisine": "Non-regional",
  "recipeCategory": "Sweets & Desserts",
  "keywords": [
    "cakes",
    "miscellaneous"
  ],
  "recipeIngredient": [
    "2 tbsp margarine",
    "2 1/2 cups chocolate cookie crumbs",
    "2 lbs cream cheese (soft)",
    "1 cup sugar",
    "4 eggs",
    "1 tsp all-purpose flour",
    "1 tsp vanilla extract",
    "1 cup sour cream",
    "1 lb refrigerated chocolate chip-cookie dough",
    "2 oz chocolate chips",
    "TOPPINGS",
    "1 pint heavy whipping cream",
    "Chocolate chips",
    "Chopped walnuts"
  ],
  "recipeInstructions": "1. Preheat oven to 325°F.\n2. Generously grease the bottom and sides of a 10-inch springform pan.\n3. Combine margarine with chocolate cookie crumbs and press onto the bottom and sides of the pan.\n4. Using an electric mixer on high speed, combine cream cheese, sugar, eggs, and flour until smooth. Add vanilla extract and sour cream, mixing just until blended.\n5. Pour half of the batter into the prepared crust.\n6. Cut cookie dough into golf ball-sized chunks and drop them into the batter. Sprinkle chocolate chips over the top.\n7. Pour remaining batter over the toppings.\n8. Bake for 60 minutes.\n9. Turn off the oven and open the door to the broil position. Allow cake to remain in the oven for an additional 30 minutes.\n10. Refrigerate until ready to serve.\n11. Remove sides of the pan and top with fresh whipped cream. Sprinkle with additional chocolate chips and chopped walnuts.",
  "url": null
}
