{
  "@type": "Recipe",
  "identifier": "blackberry-cobbler",
  "name": "Pastel de bayas silvestres",
  "recipeCuisine": "Non-regional",
  "recipeCategory": "Sweets & Desserts",
  "keywords": [
    "productos horneados",
    "pasteles de frutas",
    "postres",
    "frutas",
    "masa hojaldrada"
  ],
  "recipeIngredient": [
    "2 cucharadas de almidón de maíz",
    "1 cucharada de zumo de limón",
    "1 taza de harina",
    "1/2 cucharadita de sal",
    "6 cucharadas de mantequilla sin sal, fría, cortada en trozos",
    "1 taza de azúcar",
    "4 tazas de frambuesas, seleccionadas y enjuagadas"
  ],
  "recipeInstructions": "1. En un bol grande, mezcle el almidón de maíz con 1/4 taza de agua fría hasta que el almidón se disuelva por completo.\n2. Añada 1 taza de azúcar, zumo de limón y frambuesas a la mezcla de almidón. Combine suavemente pero completamente.\n3. Transfiera la mezcla a una sartén de hierro fundido de 8 pulgadas.\n4. En un bol separado, combine la harina, el azúcar restante, el polvo de hornear y la sal.\n5. Agregue la mantequilla fría y mezcle hasta que la textura sea similar a migas gruesas.\n6. Añada 1/4 taza de agua hirviendo y mezcle hasta formar una masa.\n7. Ponga la mezcla de frambuesas a hervir en la estufa, revolviendo ocasionalmente.\n8. Coloque cucharadas de la masa en el hervor con cuidado.\n9. Hornee el pastel en un horno precalentado a 400 °F durante 20-25 minutos o hasta que la tapa sea dorada.\n10. Sirva caliente con helado de vainilla.",
  "url": null
}
