{
  "@type": "Recipe",
  "identifier": "chocolate-chip-cake-4",
  "name": "Pastel de Chispas de Chocolate",
  "recipeCuisine": "Non-regional",
  "recipeCategory": "Sweets & Desserts",
  "keywords": [
    "pasteles",
    "chocolate",
    "postres"
  ],
  "recipeIngredient": [
    "1/2 taza de azúcar morena en cubos",
    "1/2 taza de nueces picadas",
    "1 taza de trozos de chocolate semiamargo",
    "3 tazas de harina de uso común",
    "3 1/4 tazas de azúcar",
    "1 1/4 tazas de leche",
    "1/2 taza de manteca",
    "2 1/2 cucharaditas de polvo de hornear",
    "1 cucharadita de sal",
    "1 1/2 cucharaditas de extracto de vainilla",
    "2 huevos"
  ],
  "recipeInstructions": "1. Preparar la cobertura: En un bol pequeño, mezclar la azúcar morena, las nueces picadas y la mitad de los trozos de chocolate semiamargo. Reservar.\n2. Precalentar el horno a 350°F (175°C). Engrasar y enharinar un molde para hornear rectangular de 23x33 cm.\n3. En un bol grande, combinar la harina con los ingredientes restantes, excepto los trozos de chocolate semiamargo reservados. Mezclar a baja velocidad hasta que se combinen, raspando los lados del bol regularmente.\n4. Aumentar la velocidad del mezclador a alta y batir durante 2 minutos, raspando los lados del bol ocasionalmente.\n5. Incorporar los trozos de chocolate semiamargo reservados y verter la masa en el molde preparado.\n6. Extender la cobertura sobre la masa.\n7. Hornear durante 40-45 minutos, o hasta que un palillo insertado en el centro del pastel salga limpio. Enfriar en el molde sobre una rejilla.",
  "url": null
}
