{
  "@type": "Recipe",
  "identifier": "easy-boston-cream-pie",
  "name": "Tarta de Boston Fácil",
  "recipeCuisine": "Non-regional",
  "recipeCategory": "Sweets & Desserts",
  "keywords": [
    "productos horneados",
    "postres",
    "tarta",
    "tartas"
  ],
  "recipeIngredient": [
    "18 1/4 ozs de mezcla de bizcocho amarillo con reducción de grasa",
    "1 sobre de Dream Whip® para batir",
    "1/2 cucharadita de polvo de hornear",
    "1 taza de agua fría",
    "4 claras de huevo",
    "1 cucharada de aceite de oliva",
    "1 cucharadita de extracto de vainilla puro",
    "3 ozs de mezcla de pudín de vainilla sin grasa, sin instantáneo",
    "Icing:",
    "1 taza de azúcar glas",
    "4 cucharadas de cacao en polvo",
    "1/8 cucharadita de sal",
    "1 cucharada de margarina con reducción de grasa ablandada",
    "3 cucharadas de agua caliente"
  ],
  "recipeInstructions": "1. Precalentar el horno a 350°F (175°C).\n2. Preparar dos moldes para pastel de 8 pulgadas con spray antiadherente y harina; reservar.\n3. En un bol, mezclar la mezcla de bizcocho, el batido y el polvo de hornear.\n4. En otro bol, combinar el agua, las claras, el aceite y el extracto de vainilla.\n5. Mezclar los ingredientes secos con los húmedos hasta que estén mojados.\n6. Verter uniformemente en los moldes preparados.\n7. Hornear durante 25 minutos o hasta que sea dorado. Congelar una capa para uso futuro.\n8. Preparar la mezcla de pudín según las instrucciones del paquete; enfriar.\n9. Dividir la capa de bizcocho enfriada.\n10. Extender el relleno de pudín en la base.\n11. Colocar la parte superior del bizcocho sobre la capa de pudín.\n12. Para preparar el glaseado, mezclar el azúcar glas, el cacao, la sal, la margarina y el agua caliente hasta que esté suave.\n13. Cubrir la parte superior de la tarta con el glaseado y dejar que el exceso se escurra por los lados del pastel.",
  "url": null
}
