{
  "@type": "Recipe",
  "identifier": "crescent-lasagna",
  "name": "Crescent Lasagna",
  "recipeCuisine": "Non-regional",
  "recipeCategory": "Main Dishes",
  "keywords": [
    "main dish",
    "pasta"
  ],
  "recipeIngredient": [
    "1 pound ground beef",
    "3/4 cup chopped onion",
    "1 clove garlic, minced",
    "1 tablespoon parsley flakes",
    "1/2 teaspoon dried basil leaves",
    "1/2 teaspoon oregano leaves",
    "1/2 teaspoon salt",
    "1 dash pepper",
    "6 oz tomato paste",
    "1 cup creamed cottage cheese",
    "1 egg",
    "1/4 cup grated Parmesan cheese",
    "8 oz refrigerated crescent rolls",
    "7 slices Mozzarella cheese (approximately 7x4 inches)",
    "1 tablespoon milk",
    "1 tablespoon sesame seeds"
  ],
  "recipeInstructions": "Preheat oven to 375°F.\nMEAT FILLING: In a large skillet, brown the ground beef and drain. Add all meat filling ingredients. Simmer, uncovered, for 5 minutes. The meat mixture can be made ahead and refrigerated.\nCHEESE FILLING: Combine creamed cottage cheese, egg, and Parmesan cheese.\nCRUST: Separate crescent dough into 8 rectangles. Place the dough rectangles together on an ungreased cookie sheet, overlapping edges slightly to form a rectangle about 15x13 inches. Press the perforations and edges to seal well.\nSpread half of the meat filling lengthwise down the center of the dough, stopping 1 inch from each end. Top with cheese filling; spoon remaining meat filling over top, forming three layers. Place cheese slices over the meat filling.\nFold the ends of the dough rectangle over the filling, about 1 inch. Pull the long sides of the dough over the filling, overlapping edges only a quarter inch. Pinch the overlapped edges to seal. Brush with milk and sprinkle with sesame seeds.\nBake at 375°F for 20-25 minutes or until golden brown. If preparing ahead, cover and refrigerate for 2-3 hours before baking. Increase baking time to 25-30 minutes.",
  "url": null
}
