{
  "@type": "Recipe",
  "identifier": "crispy-chicken-with-lemon-sauce",
  "name": "Crispy Chicken with Lemon Sauce",
  "recipeCuisine": "Asia & Pacific Ocean",
  "recipeCategory": "Main Dishes",
  "keywords": [
    "chicken",
    "chinese",
    "main dish",
    "meat",
    "poultry"
  ],
  "recipeIngredient": [
    "3 (3 1/2-lb) chickens",
    "Chicken stock or water",
    "Oil",
    "3 Lemons; juiced. Reserving:",
    "1 -Squeezed lemon half",
    "1/2 cup Sugar",
    "1/2 cup Water",
    "2 tbsp Soy sauce",
    "2 tbsp Cornstarch",
    "Lemon peel triangles (optional)"
  ],
  "recipeInstructions": "1. Cook the chicken in simmering chicken stock or water until nearly tender, about 20 minutes.\n2. Remove and suspend the chicken over a bowl to dry at room temperature for at least 4 hours, or until thoroughly cooled.\n3. Heat enough oil to 350°F in a wok for deep-frying whole chicken.\n4. Add the chicken and fry for 20 minutes, turning until golden on all sides.\n5. Meanwhile, combine lemon juice with the squeezed lemon half, sugar, and water in a saucepan. Bring to boil and simmer for 2 to 3 minutes until sugar is dissolved.\n6. Add 2 teaspoons of oil and soy sauce. Remove from heat and set aside.\n7. Split the chicken into halves along the back and cut into serving pieces.\n8. Reassemble on a serving platter and garnish with lemon peel triangles, if desired.\n9. Bring the reserved lemon sauce to boil again.\n10. Mix cornstarch with a small amount of cold water to make a paste and stir into the lemon sauce. Cook, stirring until slightly thickened.\n11. Spoon over chicken pieces.",
  "url": null
}
