{
  "@type": "Recipe",
  "identifier": "scallops-and-tomato-pasta",
  "name": "Scallops and Tomato Pasta",
  "recipeCuisine": "Non-regional",
  "recipeCategory": "Main Dishes",
  "keywords": [
    "main dish",
    "pasta"
  ],
  "recipeIngredient": [
    "1 lb spinach linguini or fettuccine (dried)",
    "1 lb small scallops, or large ones cut into quarters",
    "1/2 cup fresh parsley, chopped",
    "2-3 cloves garlic, minced",
    "1/2 cup white wine",
    "2 large tomatoes, chopped",
    "1 tablespoon olive oil",
    "1/4 cup pine nuts, toasted (optional)",
    "Fresh shredded or grated parmesan cheese (optional)"
  ],
  "recipeInstructions": "1. Bring a large pot of salted water to a boil and cook the pasta until al dente.\n2. In a non-stick pan over medium heat, lightly cook the garlic in olive oil for a few minutes.\n3. Toast the pine nuts until lightly browned, stirring often.\n4. Add chopped tomatoes and white wine to the pan with garlic and olive oil. Simmer for a couple of minutes, allowing the sauce to reduce slightly.\n5. Add the scallops, parsley, and lemon juice (if using) to the pan. Cook through the heat gently until the scallops are cooked through.\n6. Drain the pasta and add it to the pan with the scallop mixture. Toss everything together.\n7. Serve hot over the cooked pasta, topped with toasted pine nuts and grated parmesan cheese if desired.\nThe sauce is very light, but the dish is filling and makes 6 generous servings.",
  "url": null
}
