{
  "@type": "Recipe",
  "identifier": "spaghetti-with-meat-sauce",
  "name": "Spaghetti with Meat Sauce",
  "recipeCuisine": "Europe",
  "recipeCategory": "Main Dishes",
  "keywords": [
    "freezer meals",
    "main dish",
    "pasta"
  ],
  "recipeIngredient": [
    "1/4 pound ground beef",
    "1/4 pound Italian sausage",
    "1 onion",
    "3 cups marinara sauce",
    "1 freezer container, quart"
  ],
  "recipeInstructions": "1. Brown the ground beef and Italian sausage separately.\n2. Chop the onion and sauté it in a pan until softened.\n3. Combine the browned ground beef, browned Italian sausage, and sautéed onion in a 1-quart freezer container.\n4. Add the marinara sauce to the mixture and cover.\n5. Freeze for several hours or overnight.\nTo prepare:\n1. Thaw the spaghetti meat sauce in the refrigerator for several hours or overnight.\n2. In a small saucepan, heat the thawed sauce slowly over low heat for about 10 minutes.\n3. Serve the heated sauce over hot pasta.\n4. Garnish with green salad and fresh French bread.\nServing Ideas: Green Salad, Fresh French Bread",
  "url": null
}
