{
  "@type": "Recipe",
  "identifier": "blackened-chicken",
  "name": "Pollo a la parrilla negra",
  "recipeCuisine": "North & South America",
  "recipeCategory": "Main Dishes",
  "keywords": [
    "pollo",
    "plato principal",
    "carne",
    "ave de corral"
  ],
  "recipeIngredient": [
    "16 pechugas de pollo sin piel y sin hueso (aproximadamente 3 onzas cada una)",
    "Mezcla de especias:",
    "2 cucharadas de sal",
    "1 1/2 cucharaditas de polvo de ajo",
    "1 1/2 cucharaditas de pimienta negra",
    "1 cucharadita de pimienta blanca",
    "1 cucharadita de polvo de cebolla",
    "1 cucharadita de comino en polvo",
    "1/2 cucharadita de pimentón rojo en polvo (preferiblemente cayena)",
    "3/4 libra de mantequilla sin sal, derretida y mantenida caliente"
  ],
  "recipeInstructions": "Nota: Las pechugas deben pesar aproximadamente 3 onzas cada una, tener un grosor de 1/2 a 3/4 pulgada. Alternativamente, se pueden usar 8 muslos con hueso o una combinación de ambos.\nDeshuesar y pelar los muslos, dejando la carne en un solo trozo. Retirar el exceso de grasa. Golpear cada pechuga o fillet de muslo hasta que tengan 1/2 pulgada de grosor.\n1. Dejar que el pollo alcance la temperatura ambiente antes de sellarlo.\n2. Mezclar bien los ingredientes de la mezcla de especias en un bol pequeño.\n3. Calentar una sartén de hierro fundido grande a fuego muy alto hasta que esté extremadamente caliente y apenas forme cenizas blancas en el fondo (aproximadamente 8 minutos). El tiempo de cocción puede variar según la intensidad de la fuente de calor.\n4. Precalentar los platos de servicio en un horno a 250 °F.\n5. Antes de cocinar cada pieza, sumergirla en mantequilla derretida para que ambos lados estén bien cubiertos. Espolvorear cada filete uniformemente con la mezcla de especias usando aproximadamente 1/2 cucharadita, presionando con las manos.\n6. Colocar el filete con la piel hacia abajo en la sartén caliente, asegurándose de que todas las pliegues estén abiertos y la carne quede plana. Verter aproximadamente 1 cucharadita de mantequilla sobre el filete (tener cuidado, ya que la mantequilla puede salpicar). Si se cocinan más de un filete a la vez, colocar cada filete en la sartén antes de agregar mantequilla y especias al siguiente.\n7. Cocinar sin tapar a fuego muy alto hasta que se forme una costra por debajo, aproximadamente 2 minutos. El tiempo de cocción variará según el grosor del filete y la temperatura de la sartén; observar la formación de una línea blanca mientras se cocina.\n8. Dar la vuelta a los filetes y verter aproximadamente 1 cucharadita más de mantequilla derretida sobre cada uno. Cocinar solo hasta que la carne esté bien cocida, aproximadamente 2 minutos más.\n9. Servir los filetes de pollo con la parte superior crujiente mientras estén calientes.\n10. Limpiar la sartén después de cocinar cada lote y repetir el procedimiento de sellado con las piezas de pollo restantes.\nPara servir, colocar 2 filetes de pechuga o 1 fillet de muslo en cada plato caliente. Si se usa un plato grande, no apilar los filetes.",
  "url": null
}
