{
  "@type": "Recipe",
  "identifier": "stir-fry-of-broccoli-chicken",
  "name": "Salteado de Brócoli y Pollo",
  "recipeCuisine": "Asia & Pacific Ocean",
  "recipeCategory": "Main Dishes",
  "keywords": [
    "pollo",
    "plato principal",
    "carne",
    "oriental",
    "ave de corral"
  ],
  "recipeIngredient": [
    "1 lb (450 g) de pechugas de pollo sin piel ni hueso, cortadas en tiras",
    "6 tazas de floretes de brócoli (aproximadamente 2 libras)",
    "2 pimientos rojos o verdes grandes, cortados en cuartos a lo largo y en tiras finas",
    "1 cebolla grande, cortada en rodajas de 1/4 cm de grosor",
    "2 dientes de ajo picados",
    "1/2 cucharadita de tomillo seco (triturado)",
    "1 cucharada de albahaca seca triturada",
    "1/2 cucharadita de pimienta negra molida",
    "1/2 cucharadita de sal",
    "4 cucharadas de parmesano fresco rallado"
  ],
  "recipeInstructions": "1. Golpea las pechugas de pollo entre dos hojas de papel para hornear hasta que tengan un grosor de 1/4 cm. Envuelve cada pechuga en plástico y congela hasta que estén firmes pero no duras.\n2. Corta el pollo en tiras finas.\n3. Cubre los floretes de brócoli con agua fría en un bol mediano.\n4. Enjuaga una sartén pesada con spray vegetal.\n5. Añade aceite de oliva a la sartén y calienta a fuego alto durante 1 minuto.\n6. Agrega los pimientos (rojos o verdes), cebolla, ajo, albahaca, tomillo, pimienta y romero a la sartén. Saltea durante 2 minutos.\n7. Escurre el brócoli, pero no sacudas el exceso de agua. Añádelo a la sartén. Saltea durante 3 minutos.\n8. Reduce el fuego a medio-bajo, tapa y deja cocer a vapor durante 2 minutos.\n9. Incorpora el pollo. Tapa y deja cocer hasta que el pollo esté casi hecho, aproximadamente 1 minuto.\n10. Desenfría la tapa y aumenta el fuego. Saltea hasta que se reduzca ligeramente el líquido, aproximadamente 1 minuto.\n11. Divide entre platos calientes. Espolvorea 1 cucharada de parmesano sobre cada porción.",
  "url": null
}
