{
  "@type": "Recipe",
  "identifier": "summer-squash-casserole-5",
  "name": "Cazuela de Calabacín de Verano",
  "recipeCuisine": "Non-regional",
  "recipeCategory": "Main Dishes",
  "keywords": [
    "cazuelas",
    "plato principal",
    "verduras"
  ],
  "recipeIngredient": [
    "6 tazas de calabacín de verano en rodajas",
    "1/4 taza de cebolla picada",
    "1 lata de sopa cremosa de pollo",
    "1 taza de crema agria",
    "1 taza de zanahorias ralladas",
    "8 onzas de pan rizado con hierbas",
    "1/2 taza de margarina derretida"
  ],
  "recipeInstructions": "1. Cocinar el calabacín y la cebolla en agua hirviendo durante 5 minutos.\n2. Escurrir y reservar.\n3. Mezclar la sopa de pollo con la crema agria. Incorporar las zanahorias.\n4. Doblar el calabacín y la cebolla escurridos.\n5. En un bol aparte, mezclar el pan rizado con la margarina derretida.\n6. Extender la mitad del pan rizado en un molde para hornear de 20 cm x 30 cm.\n7. Colocar la mezcla de verduras encima.\n8. Espolvorear con el resto del pan rizado.\n9. Hornear a 175°C durante 25-30 minutos o hasta que esté caliente.",
  "url": null
}
