{
  "@type": "Recipe",
  "identifier": "tuna-casserole-microwave-style",
  "name": "Cazuela de Atún al Microondas",
  "recipeCuisine": "Non-regional",
  "recipeCategory": "Main Dishes",
  "keywords": [
    "cazuelas",
    "pescado",
    "plato principal"
  ],
  "recipeIngredient": [
    "2 latas de atún en cubos - 6 onzas cada una",
    "3 tazas de macarrones secos sin cocinar",
    "1/2 taza de apio picado",
    "1/3 taza de cebolla verde en rodajas",
    "1/2 taza de crema agria",
    "2 cucharadas de mostaza seca",
    "1/2 taza de mayonesa Miracle Whip",
    "1/4 cucharadita de tomillo",
    "1/4 cucharadita de sal",
    "1 calabacín en rodajas",
    "1 taza de queso Monterey Jack rallado",
    "1 tomate picado"
  ],
  "recipeInstructions": "1. Escurrir y desmenuzar el atún; reservar.\n2. Cocinar los macarrones según las instrucciones del fabricante, luego escurrirlos y enjuagarlos con agua caliente.\n3. Mezclar los macarrones con el atún, el apio y la cebolla verde.\n4. Incorporar la crema agria, la mostaza, la mayonesa Miracle Whip, el tomillo y la sal.\n5. Extender la mitad de la mezcla en un plato para cazuela engrasado de 2 cuartos.\n6. Cubrir con la mitad del calabacín, luego agregar el resto de la mezcla y nuevamente cubrir con el calabacín restante.\n7. Tapar la cazuela; cocinar al microondas a potencia alta durante 6-8 minutos.\n8. Espolvorear con queso y tomate; cocinar al microondas a potencia alta durante 2 minutos más.\n9. Dejar reposar durante 3 minutos antes de servir.\nNotas: Los tiempos de microondas varían según la potencia del aparato. El que utilizo es un horno Sanyo de 1000 vatios. Este plato contiene aproximadamente 400 calorías y 24 gramos de carbohidratos por porción.",
  "url": null
}
