{
  "@type": "Recipe",
  "identifier": "zucchini-pie",
  "name": "Tarta de Calabacín",
  "recipeCuisine": "Non-regional",
  "recipeCategory": "Main Dishes",
  "keywords": [
    "tartas para la cena",
    "plato principal"
  ],
  "recipeIngredient": [
    "5 calabacines",
    "3 zanahorias",
    "1 cucharada de vinagre de vino blanco",
    "1 lata de sopa de setas vegetales",
    "1 cebolla",
    "3 rebanadas de pan blanco",
    "Mantequilla baja en grasa",
    "1 diente de ajo"
  ],
  "recipeInstructions": "1. Cortar los calabacines y picar finamente la cebolla. Cocinar en el microondas hasta que estén ligeramente cocidos.\n2. Rallar las zanahorias.\n3. Abrir la lata de sopa y verter en una sartén. Añadir la mezcla de calabacín, las zanahorias ralladas y el vinagre de vino blanco. Cocinar hasta calentar/cocinar completamente (aproximadamente 10 minutos).\n4. Calentar la parrilla.\n5. Machacar el ajo con la mantequilla baja en grasa.\n6. Cortar el pan en palitos.\n7. Colocar la mezcla de setas en un recipiente apto para horno poco profundo. Cubrir la parte superior con los palitos de pan y colocar bajo la parrilla hasta que el pan se dore y cruja.\nDisfrutar inmediatamente.",
  "url": null
}
