{
  "@type": "Recipe",
  "identifier": "spicy-lentil-patties",
  "name": "Pasteles de lentejas picantes",
  "recipeCuisine": "Non-regional",
  "recipeCategory": "Restricted & Special Diets",
  "keywords": [
    "dietas especiales",
    "vegetariano"
  ],
  "recipeIngredient": [
    "1 taza de lentejas, enjuagadas y escurridas",
    "3 tazas de agua",
    "1 cucharadita de polvo de curry",
    "una pizca de sal",
    "1 cucharadita de cilantro molido",
    "1 cucharadita de comino molido",
    "1 cucharada de aceite de oliva",
    "1/4 taza de zanahoria, picada finamente",
    "2 dientes de ajo, picados",
    "1 cebolla grande, picada",
    "1 1/2 tazas de pan rallado integral",
    "2 cucharadas de harina de trigo",
    "2 cucharadas de pasta de tomate mezclada con 1 cucharada de salsa de soja"
  ],
  "recipeInstructions": "1. Enjuagar las lentejas y agregarlas al agua. Llevar a ebullición, reducir el fuego, agregar el polvo de curry, la sal, el cilantro y el comino. Cubrir la sartén y cocinar durante 35 a 45 minutos hasta que estén tiernas. Retirar y dejar tapadas.\n2. Calentar el aceite de oliva en una sartén y saltear la zanahoria, el ajo y la cebolla. Dejar enfriar ligeramente.\n3. Agregar las lentejas, los vegetales fríos, el pan rallado (o molido finamente), la harina de trigo y la mezcla de pasta de tomate/salsa de soja a un bol grande. Mezclar bien hasta que todos los ingredientes estén distribuidos uniformemente.\n4. Formar la mezcla en 12 hamburguesas y colocarlas sobre una bandeja para hornear engrasada.\n5. Hornear a 350 grados durante 20 minutos. Darles la vuelta y hornear por otros 20 minutos, o hasta que estén doradas y crujientes.",
  "url": null
}
