{
  "@type": "Recipe",
  "identifier": "lavender-liqueur",
  "name": "Licor de lavanda",
  "recipeCuisine": "Non-regional",
  "recipeCategory": "On the Side",
  "keywords": [
    "alcohol",
    "bebidas",
    "licores",
    "guarniciones"
  ],
  "recipeIngredient": [
    "6 cucharadas de pétalos de lavanda secos",
    "1 quinta parte de vodka de 80 grados",
    "1 taza de jarabe de azúcar"
  ],
  "recipeInstructions": "1. Coloca los pétalos de lavanda seca en un frasco limpio.\n2. Vierte el vodka sobre los pétalos, asegurándote de que queden completamente sumergidos.\n3. Cierra bien el frasco y guárdalo en un lugar fresco y oscuro durante una semana.\n4. Pasada una semana, cuela la mezcla a través de un paño de queso hacia otro recipiente.\n5. Presiona el paño de queso para extraer todo el líquido posible de los pétalos de lavanda.\n6. Mezcla el jarabe de azúcar hasta que esté bien combinado.\n7. Deja reposar el licor durante 24 horas adicionales antes de disfrutar.",
  "url": null
}
