{
  "@type": "Recipe",
  "identifier": "west-indian-curry-powder",
  "name": "Polvo de curry del Caribe Occidental",
  "recipeCuisine": "Asia & Pacific Ocean",
  "recipeCategory": "On the Side",
  "keywords": [
    "mezclas",
    "acompañamientos",
    "especias"
  ],
  "recipeIngredient": [
    "25 gramos (1 onza) de semillas de cilantro",
    "una cucharada de anís en grano",
    "una cucharada de comino en grano",
    "una cucharada de mostaza negra en grano",
    "una cucharada de fenogreco en grano",
    "una cucharada de pimienta negra en grano",
    "un trozo de canela",
    "2 cucharadas de jengibre en polvo",
    "2 cucharadas de cúrcuma en polvo"
  ],
  "recipeInstructions": "Los hindúes que migraron a las Indias Occidentales en el siglo XIX introdujeron sus mezclas de especias a las islas, y los curries se han popularizado en toda la región. Tuesta todos los granos enteros durante unos cinco minutos. Deja que se enfríen completamente antes de molerlos y mezclarlos con el jengibre y la cúrcuma. Almacena el polvo en un frasco hermético; durará de tres a cuatro meses.",
  "url": null
}
