{
  "@type": "Recipe",
  "identifier": "improved-cornbread",
  "name": "Pan de maíz mejorado",
  "recipeCuisine": "Non-regional",
  "recipeCategory": "Baked Goods",
  "keywords": [
    "productos horneados",
    "panes"
  ],
  "recipeIngredient": [
    "2 huevos",
    "2 cucharadas de polvo de hornear",
    "1 cucharadita de bicarbonato de sodio",
    "1/2 cucharadita de sal",
    "2 cucharadas de miel",
    "2 cucharadas de aceite vegetal (se puede usar mantequilla o Crisco)",
    "1 taza de buttermilk",
    "1 taza de harina blanca",
    "1 taza de maicena"
  ],
  "recipeInstructions": "1. Precalentar el horno a 400 °F y engrasar los moldes o una sartén.\n2. Mezclar en un bol grande los ingredientes secos: polvo de hornear, bicarbonato de sodio, sal, harina y maicena.\n3. En otro bol, batir juntos los huevos, la miel, el aceite vegetal y el buttermilk.\n4. Verter la mezcla húmeda sobre los ingredientes secos y remover hasta combinarlos.\n5. Verter la masa en los moldes engrasados, llenándolos aproximadamente hasta la mitad.\n6. Hornear durante 20-25 minutos o hasta que un palillo insertado en el centro salga limpio.\n7. Servir caliente.",
  "url": null
}
