{
  "@type": "Recipe",
  "identifier": "sour-dough-starter",
  "name": "Massa madre ácida",
  "recipeCuisine": "Non-regional",
  "recipeCategory": "Baked Goods",
  "keywords": [
    "productos horneados",
    "pan",
    "panes"
  ],
  "recipeIngredient": [
    "1 sobre de levadura seca",
    "2 tazas y media de agua tibia",
    "2 tazas de harina de uso común",
    "1 cucharada de azúcar o miel"
  ],
  "recipeInstructions": "1. Disolver la levadura en medio vaso de agua.\n2. Añadir el resto del agua, la harina y el azúcar (o miel). Mezclar hasta obtener una masa suave. Cubrir con un paño de cocina.\n3. Dejar reposar a temperatura ambiente durante 5 a 10 días o hasta que esté espumosa. Remover 2 o 3 veces al día.\n4. Para almacenar, transferir a un tarro y cubrir con un paño; refrigerar.\n5. Para usar, dejar a temperatura ambiente.\n6. Para reponer después de usar (1 taza), mezclar tres cuartos de taza de harina, tres cuartos de taza de agua y una cucharadita de azúcar o miel en la cantidad restante. Cubrir y dejar reposar a temperatura ambiente hasta que esté espumosa. Refrigerar para uso posterior.\n7. Si el masa madre no se usa en 10 días, añadir una cucharadita de azúcar o miel. Repetir cada 10 días hasta su uso.",
  "url": null
}
