{
  "@type": "Recipe",
  "identifier": "chicken-enchilada-crepes",
  "name": "Crepes de pollo enchiladas",
  "recipeCuisine": "Non-regional",
  "recipeCategory": "Breakfast",
  "keywords": [
    "pollo",
    "crepes",
    "plato principal",
    "carne",
    "ave de corral"
  ],
  "recipeIngredient": [
    "Salsa:",
    "1/4 taza cebolla finamente picada",
    "1 cucharada margarina",
    "1 lata de salsa de tomate (400 g)",
    "1 lata de chiles verdes, salsa (400 ml)",
    "1 cucharadita de polvo de chile",
    "1/4 cucharadita de sal de ajo",
    "Relleno:",
    "3 tazas de pollo o pavo cocido y desmenuzado",
    "2 tazas de crema agria",
    "2 tazas de queso Cheddar rallado",
    "18 crepes cocidos",
    "Decoración:",
    "1 aguacate maduro o cebolla verde picada",
    "Crema agria al gusto"
  ],
  "recipeInstructions": "Salsa: Sofreír la cebolla en mantequilla o margarina en una sartén pequeña hasta que esté tierna. Añadir el resto de los ingredientes, dejar hervir a fuego lento durante 15 minutos sin tapar.\nRelleno: Mezclar el pollo desmenuzado con la crema agria y el queso. Utilizar aproximadamente 1,5 cucharadas para cada crepe. Rellenar los crepes colocando la masa extendida en el centro de cada uno. Extender el relleno en una línea a lo largo del crepe. Enrollar el crepe en estilo rollo de gelatina y colocar con el borde abierto hacia abajo en un molde para hornear de 23 x 33 cm.\nHornear los crepes rellenos en horno precalentado a 180 °C durante unos 20 minutos o hasta que estén calientes y burbujeantes. Los crepes se pueden rellenar e hornear inmediatamente o conservar y descongelar. Descongelar ligeramente y hornear como se indica, añadiendo unos minutos adicionales.\nServir con salsa caliente por encima y decorar con rodajas de aguacate o cebolla verde y un chorrito de crema agria.",
  "url": null
}
