{
  "@type": "Recipe",
  "identifier": "parsnip-cakes",
  "name": "Parsnip Cakes",
  "recipeCuisine": "Non-regional",
  "recipeCategory": "Fruits, Grains & Vegetables",
  "keywords": [
    "vegetables"
  ],
  "recipeIngredient": [
    "1 lb Parsnips",
    "2 tbsp Flour",
    "1 pinch Mace",
    "2 tbsp Melted butter",
    "Salt and pepper",
    "Large egg",
    "8 tbsp Breadcrumbs (heaping)",
    "Oil for frying"
  ],
  "recipeInstructions": "1. Peel and slice the parsnips.\n2. Boil the sliced parsnips in salted water until tender. Drain well.\n3. Mash the cooked parsnips thoroughly.\n4. Add flour, mace, melted butter, salt, and pepper to the mashed parsnips. Mix until combined.\n5. Form the mixture into small, flat, round cakes.\n6. Beat the large egg in a shallow dish.\n7. Dip each cake first into the beaten egg, then coat with breadcrumbs.\n8. Heat oil in a deep skillet or pot to frying temperature (about 350°F/175°C).\n9. Carefully place the breadcrumb-coated parsnip cakes into the hot oil.\n10. Fry until brown on both sides, turning once halfway through cooking.\n11. Remove the cakes from the oil using tongs and allow them to drain on a paper towel-lined plate before serving.",
  "url": null
}
