{
  "@type": "Recipe",
  "identifier": "prosciutto-di-parma-with-grilled-fresh-fig-salad",
  "name": "Prosciutto Di Parma with Grilled Fresh Fig Salad",
  "recipeCuisine": "Non-regional",
  "recipeCategory": "Fruits, Grains & Vegetables",
  "keywords": [
    "salads"
  ],
  "recipeIngredient": [
    "8 ounces Prosciutto di Parma, sliced paper thin",
    "12 figs, cut in half",
    "2 tablespoons fresh rosemary leaves, chopped",
    "2 tablespoons balsamic vinegar",
    "12 sprigs Italian parsley",
    "1/2 pound arugula leaves, washed and spun dry, to yield 2 cups",
    "3 tablespoons extra virgin olive oil"
  ],
  "recipeInstructions": "1. Preheat grill or broiler.\n2. Place the 12 fig halves cut side down on the grill and cook for 3 minutes. Remove and allow to cool.\n3. In a mixing bowl, toss grilled figs, raw figs, rosemary, balsamic vinegar, Italian parsley, arugula, and extra virgin olive oil. Gently mix with hands so as not to break the figs.\n4. Divide the paper-thin Prosciutto onto 4 plates.\n5. Divide the fig salad and place on top of Prosciutto.\n6. Serve immediately.\nYield: 4 servings",
  "url": null
}
