{
  "@type": "Recipe",
  "identifier": "warm-tortellini-salad",
  "name": "Warm Tortellini Salad",
  "recipeCuisine": "Non-regional",
  "recipeCategory": "Fruits, Grains & Vegetables",
  "keywords": [
    "pasta",
    "salads"
  ],
  "recipeIngredient": [
    "2 packages (9 oz each) fresh cheese - tortellini",
    "2 cups broccoli florets (1 bunch)",
    "1/2 lb Havarti cheese, cut into 1/4-inch cubes",
    "Half of a 7 1/4 oz jar roasted red peppers, thinly sliced",
    "1/2 cup reduced-calorie Dijon vinaigrette dressing"
  ],
  "recipeInstructions": "Serves 4\n1. Cook the tortellini in a large pot of boiling water according to the package directions. Add the broccoli for the last 5 minutes of cooking.\n2. Combine cheese, peppers, and dressing in a bowl.\n3. Drain pasta and broccoli, then add them to the cheese mixture with the peppers.",
  "url": null
}
