{
  "@type": "Recipe",
  "identifier": "carbonnade-belgian-beer-stew-2",
  "name": "Carbonnade (Belgian Beer Stew)",
  "recipeCuisine": "Europe",
  "recipeCategory": "Soups & Stuff",
  "keywords": [
    "beef",
    "soups",
    "stews"
  ],
  "recipeIngredient": [
    "3 lb Chuck roast",
    "1 Smoked ham hock, (optional)",
    "1/2 cup Oil",
    "2 1/2 tsp Salt",
    "1 large Onion, thinly sliced",
    "3 tbsp Flour",
    "Beer",
    "1 cup Beef broth",
    "1/2 tsp Black pepper",
    "2 tsp Sugar",
    "2 tbsp Parsley flakes",
    "1 pinch Marjoram",
    "1 pinch Thyme",
    "1 Clove Garlic, chopped fine",
    "4 Carrots, cut into 1-inch pieces",
    "3/4 cup Walnuts, (optional)",
    "2 tbsp Red wine vinegar",
    "2 tbsp Scotch whiskey"
  ],
  "recipeInstructions": "1. Cut beef into 1 x 2 inch strips.\n2. Remove ham from bone and cut into cubes. Brown beef and ham in oil in a large skillet. Lift meat out, sprinkle with 1 tsp salt, and set aside.\n3. Brown onions in the same oil. Lift onions out, and set aside.\n4. Drain and save all but 3 tbsp of the oil.\n5. Sift flour into the hot oil to create a light brown roux.\n6. Gradually add 1 1/2 cups beef broth, stirring until the mixture boils.\n7. Add the remaining beef broth, salt, pepper, sugar, herbs, and garlic. Layer meat, onions, and carrots in a large casserole dish. Add sauce and enough beer to cover the meat. Cover and cook in a 300°F oven for 2 1/2 hours (or on the stove top). Check occasionally and add beer if needed.\n8. Shortly before serving, sauté walnuts in the reserved oil until crisp. Do not scorch. Add walnuts to the stew.\n9. Just before serving, add vinegar and Scotch whiskey.",
  "url": null
}
